pymesis/__init__.py
pymesis/pymesis.py
pymesis-0.2.0.dist-info/LICENSE
pymesis-0.2.0.dist-info/WHEEL
pymesis-0.2.0.dist-info/METADATA
pymesis-0.2.0.dist-info/RECORD
