Metadata-Version: 2.1
Name: pymesis
Version: 0.2.0
Summary: Memoization decorator for Python, with optional TTL
Author: Daniel Hjertholm
Author-email: daniel.hjertholm@icloud.com
Requires-Python: >=3.8,<=3.10
Classifier: Programming Language :: Python :: 3
Classifier: Programming Language :: Python :: 3.10
Classifier: Programming Language :: Python :: 3.8
Classifier: Programming Language :: Python :: 3.9
